wvutils/__init__.py
wvutils/args.py
wvutils/aws.py
wvutils/compat.py
wvutils/constants.py
wvutils/datetime.py
wvutils/errors.py
wvutils/general.py
wvutils/parquet.py
wvutils/path.py
wvutils/proxies.py
wvutils/type_aliases.py
wvutils-2.0.0.dist-info/LICENSE
wvutils-2.0.0.dist-info/METADATA
wvutils-2.0.0.dist-info/WHEEL
wvutils-2.0.0.dist-info/top_level.txt
wvutils-2.0.0.dist-info/RECORD
