Metadata-Version: 2.1
Name: wvutils
Version: 2.0.0
Summary: Collection of common utilities
Author-email: The Phosmic Development Team <dev@phosmic.com>
License:                     GNU GENERAL PUBLIC LICENSE
Project-URL: homepage, https://pypi.org/project/wvutils/
Project-URL: repository, https://github.com/Phosmic/wvutils
Project-URL: issues, https://github.com/Phosmic/wvutils/issues
Keywords: utilities
Classifier: Development Status :: 3 - Alpha
Classifier: Intended Audience :: Developers
Classifier: License :: OSI Approved :: GNU General Public License v3 or later (GPLv3+)
Classifier: Natural Language :: English
Classifier: Operating System :: OS Independent
Classifier: Programming Language :: Python
Classifier: Programming Language :: Python :: 3
Classifier: Programming Language :: Python :: 3 :: Only
Classifier: Programming Language :: Python :: 3.10
Classifier: Programming Language :: Python :: 3.11
Classifier: Programming Language :: Python :: 3.12
Classifier: Programming Language :: Python :: 3.13
Classifier: Topic :: Utilities
Classifier: Topic :: Software Development
Classifier: Topic :: Software Development :: Libraries
Classifier: Topic :: Software Development :: Libraries :: Python Modules
Requires-Python: <4,>=3.10
License-File: LICENSE
Requires-Dist: boto3>=1.18.44
Requires-Dist: botocore>=1.21.44
Requires-Dist: cloudpickle>=2.0.0
Requires-Dist: google-re2>=1.0
Requires-Dist: lxml>=4.6.3
Requires-Dist: numpy>=1.21.2
Requires-Dist: pandas>=1.3.3
Requires-Dist: pyarrow>=12.0.0
Requires-Dist: requests>=2.26.0
Requires-Dist: s3fs>=0.4.2
Requires-Dist: python-rapidjson>=1.5
Requires-Dist: urllib3>=1.26.6
